gufo/acme/__init__.py
gufo/acme/acme.py
gufo/acme/error.py
gufo/acme/log.py
gufo/acme/py.typed
gufo/acme/types.py
gufo/acme/clients/__init__.py
gufo/acme/clients/base.py
gufo/acme/clients/dav.py
gufo/acme/clients/powerdns.py
gufo/acme/clients/web.py
gufo_acme-0.6.0.dist-info/licenses/LICENSE.md
gufo_acme-0.6.0.dist-info/METADATA
gufo_acme-0.6.0.dist-info/WHEEL
gufo_acme-0.6.0.dist-info/top_level.txt
gufo_acme-0.6.0.dist-info/RECORD
